CHANGES.md
freesif/__init__.py
freesif/calc/__init__.py
freesif/calc/general.py
freesif/calc/principal.py
freesif/calc/vonmises.py
freesif/data/__init__.py
freesif/data/file.py
freesif/data/helpers.py
freesif/data/hydrodata.py
freesif/data/sifdata.py
freesif/data/strucdata.py
freesif/exceptions.py
freesif/sequentialparser/__init__.py
freesif/sequentialparser/parsers.py
freesif/sequentialparser/sequentialfiles.py
freesif/sequentialparser/sif2hdf5.py
freesif/utils/__init__.py
freesif/utils/vtfdata.py
freesif/utils/writers.py
freesif-0.2.0.dist-info/LICENCE.txt
freesif-0.2.0.dist-info/METADATA
freesif-0.2.0.dist-info/WHEEL
freesif-0.2.0.dist-info/RECORD
