Metadata-Version: 2.1
Name: freesif
Version: 0.2.0
Summary: Get data from Sesam Interface Files
Home-page: https://github.com/agrav/freesif
License: MIT
Keywords: sesam,structural,hydrodynamic
Author: Audun Gravdal Johansen
Author-email: audun.gravdal.johansen@gmail.com
Requires-Python: >=3.10,<4.0
Classifier: Development Status :: 4 - Beta
Classifier: License :: OSI Approved :: MIT License
Classifier: Programming Language :: Python :: 3
Classifier: Programming Language :: Python :: 3.10
Classifier: Programming Language :: Python :: 3.11
Classifier: Programming Language :: Python :: 3.12
Classifier: Programming Language :: Python :: 3.13
Requires-Dist: h5py (>=3.9.0,<4.0.0)
Requires-Dist: numpy (>=2.2.0,<3.0.0)
Requires-Dist: tables (>=3.8.0,<4.0.0)
Project-URL: Repository, https://github.com/agrav/freesif
Project-URL: issues, https://github.com/agrav/freesif/issues
